affine_gaps.py
affine_gaps-0.2.3.dist-info/METADATA
affine_gaps-0.2.3.dist-info/WHEEL
affine_gaps-0.2.3.dist-info/entry_points.txt
affine_gaps-0.2.3.dist-info/licenses/LICENSE
affine_gaps-0.2.3.dist-info/RECORD
