Metadata-Version: 2.4
Name: affine-gaps
Version: 0.2.3
Summary: Numba-accelerated Python implementation of affine gap penalty extensions for Needleman-Wunsch and Smith-Waterman algorithms
Author-email: Ash Vardanian <1983160+ashvardanian@users.noreply.github.com>
License-File: LICENSE
Keywords: affine gaps,bioinformatics,numba,sequence alignment
Classifier: License :: OSI Approved :: Apache Software License
Classifier: Operating System :: OS Independent
Classifier: Programming Language :: Python :: 3
Requires-Python: >=3.6
Requires-Dist: colorama
Requires-Dist: numpy
Provides-Extra: dev
Requires-Dist: biopython; extra == 'dev'
Requires-Dist: pytest; extra == 'dev'
Requires-Dist: pytest-repeat; extra == 'dev'
Requires-Dist: stringzilla; extra == 'dev'
Provides-Extra: numba
Requires-Dist: numba; extra == 'numba'
